{
    "data": [
      {"name": "Bogotá"},
      {"name": "Medellín"},
      {"name": "Cali"},
      {"name": "Barranquilla"},
      {"name": "Cartagena"},
      {"name": "Santa Marta"},
      {"name": "Bucaramanga"},
      {"name": "Pereira"},
      {"name": "Manizales"},
      {"name": "Cúcuta"},
      {"name": "Villavicencio"},
      {"name": "Pasto"},
      {"name": "Ibagué"},
      {"name": "Neiva"},
      {"name": "Popayán"},
      {"name": "Tunja"},
      {"name": "Sincelejo"},
      {"name": "Valledupar"},
      {"name": "Montería"},
      {"name": "Arauca"},
      {"name": "Envigado"},
      {"name": "Itagüí"},
      {"name": "Copacabana"},
      {"name": "Barbosa"},
      {"name": "Girardota"},
      {"name": "Guatapé"},
      {"name": "Guarne"},
      {"name": "Rionegro"},
      {"name": "La Estrella"},
      {"name": "Sabaneta"},
      {"name": "Puerto Berrío"},
      {"name": "Amagá"},
      {"name": "Sonsón"},
      {"name": "El Retiro"},
      {"name": "Fredonia"},
      {"name": "Yarumal"},
      {"name": "Marinilla"},
      {"name": "La Ceja"},
      {"name": "Andes"},
      {"name": "Urrao"},
      {"name": "Chigorodó"},
      {"name": "San Pedro"},
      {"name": "Turbo"},
      {"name": "Yolombó"},
      {"name": "Jericó"},
      {"name": "Betulia"},
      {"name": "La Pintada"},
      {"name": "San Carlos"},
      {"name": "Cañasgordas"},
      {"name": "Necoclí"},
      {"name": "Apartadó"},
      {"name": "Maceo"},
      {"name": "Sopetrán"},
      {"name": "Nariño"},
      {"name": "La Unión"},
      {"name": "Pueblorrico"},
      {"name": "Támesis"},
      {"name": "Venecia"},
      {"name": "Salgar"},
      {"name": "Bolívar"},
      {"name": "Santa Fe de Antioquia"},
      {"name": "Anzá"},
      {"name": "San Jerónimo"},
      {"name": "San Juan de Urabá"},
      {"name": "San Roque"},
      {"name": "Liborina"},
      {"name": "Concordia"},
      {"name": "San Andrés de Cuerquía"},
      {"name": "Margarita"},
      {"name": "Campamento"},
      {"name": "Caracolí"},
      {"name": "Don Matías"},
      {"name": "Santa Rosa de Osos"},
      {"name": "Guadalupe"},
      {"name": "Belmira"},
      {"name": "Gómez Plata"},
      {"name": "San Pedro de Urabá"},
      {"name": "Mutatá"},
      {"name": "Briceño"},
      {"name": "Caicedo"},
      {"name": "El Bagre"},
      {"name": "Remedios"},
      {"name": "San Francisco"},
      {"name": "Cocorná"},
      {"name": "Granada"},
      {"name": "Frontino"},
      {"name": "San Luis"},
      {"name": "Alejandría"},
      {"name": "Arboletes"},
      {"name": "San José de la Montaña"},
      {"name": "Valdivia"},
      {"name": "San José de la Montaña"},
      {"name": "Valdivia"},
      {"name": "Murindó"},
      {"name": "Yalí"},
      {"name": "San Rafael"},
      {"name": "Amalfi"},
      {"name": "Giraldo"},
      {"name": "Sabanalarga"},
      {"name": "San Vicente"},
      {"name": "Campamento"},
      {"name": "Dabeiba"},
      {"name": "Zaragoza"},
      {"name": "Tarazá"},
      {"name": "Zaragoza"},
      {"name": "Tarazá"},
      {"name": "Cáceres"},
      {"name": "Caucasia"},
      {"name": "El Bagre"},
      {"name": "Nechí"},
      {"name": "Puerto Nare"},
      {"name": "Segovia"},
      {"name": "El Carmen de Viboral"},
      {"name": "El Peñol"},
      {"name": "San Vicente Ferrer"},
      {"name": "San Francisco"},
      {"name": "Cocorná"},
      {"name": "Granada"},
      {"name": "Frontino"},
      {"name": "San Carlos"},
      {"name": "Valparaíso"},
      {"name": "Amagá"},
      {"name": "Támesis"},
      {"name": "Titiribí"},
      {"name": "Venecia"},
      {"name": "Alejandría"},
      {"name": "Argelia"},
      {"name": "Armenia"},
      {"name": "Barbosa"},
      {"name": "Betania"},
      {"name": "Betulia"},
      {"name": "Bolívar"},
      {"name": "Briceño"},
      {"name": "Buriticá"},
      {"name": "Caicedo"},
      {"name": "Caldas"},
      {"name": "Campamento"},
      {"name": "Caracolí"},
      {"name": "Carmen de Viboral"},
      {"name": "Carolina"},
      {"name": "Caucasia"},
      {"name": "Chigorodó"},
      {"name": "Cisneros"},
      {"name": "Cocorná"},
      {"name": "Concordia"},
      {"name": "Dabeiba"},
      {"name": "Don Matías"},
      {"name": "Ebéjico"},
      {"name": "El Bagre"},
      {"name": "El Carmen de Viboral"},
      {"name": "El Peñol"},
      {"name": "El Retiro"},
      {"name": "El Santuario"},
      {"name": "Entrerrios"},
      {"name": "Envigado"},
      {"name": "Fredonia"},
      {"name": "Frontino"},
      {"name": "Giraldo"},
      {"name": "Girardota"},
      {"name": "Granada"},
      {"name": "Guadalupe"},
      {"name": "Guarne"},
      {"name": "Guatapé"},
      {"name": "Heliconia"},
      {"name": "Hispania"},
      {"name": "Itagüí"},
      {"name": "Jardín"},
      {"name": "Jerico"},
      {"name": "La Ceja"},
      {"name": "La Estrella"},
      {"name": "La Pintada"},
      {"name": "La Unión"},
      {"name": "Liborina"},
      {"name": "Maceo"},
      {"name": "Marinilla"},
      {"name": "Montebello"},
      {"name": "Murindó"},
      {"name": "Mutatá"},
      {"name": "Nariño"},
      {"name": "Nechí"},
      {"name": "Necoclí"},
      {"name": "Pueblorrico"},
      {"name": "Puerto Berrío"},
      {"name": "Puerto Nare"},
      {"name": "Rionegro"},
      {"name": "Sabanalarga"},
      {"name": "Sabaneta"},
      {"name": "Salgar"},
      {"name": "San Andrés de Cuerquía"},
      {"name": "San Carlos"},
      {"name": "San Francisco"},
      {"name": "San Jerónimo"},
      {"name": "San José de la Montaña"},
      {"name": "San Juan de Urabá"},
      {"name": "San Luis"},
      {"name": "San Pedro de Urabá"},
      {"name": "San Rafael"},
      {"name": "San Roque"},
      {"name": "San Vicente"},
      {"name": "Santa Bárbara"},
      {"name": "Santa Fé de Antioquia"},
      {"name": "Santo Domingo"},
      {"name": "Segovia"},
      {"name": "Sopetrán"},
      {"name": "Tarazá"},
      {"name": "Titiribí"},
      {"name": "Toledo"},
      {"name": "Turbo"},
      {"name": "Uramita"},
      {"name": "Valdivia"},
      {"name": "Valparaíso"},
      {"name": "Vegachí"},
      {"name": "Yalí"},
      {"name": "Yarumal"},
      {"name": "Yolombó"},
      {"name": "Yondó"},
      {"name": "Zaragoza"}
    ]
  }
  